{"url":"http://m4dz.github.io/prwd-workshop/origin/index.html","phantomCacheEnabled":"no","taskName":"performance","domReadystateLoading":0,"domReadystateInteractive":0,"windowOnload":0,"elapsedLoadTime":70,"numberOfResources":3,"totalResourcesTime":65,"slowestResource":"http://m4dz.github.io/prwd-workshop/origin/index.html","largestResource":"http://m4dz.github.io/prwd-workshop/origin/index.html","totalResourcesSize":13.939,"nonReportingResources":0,"timeStamp":1413587814975,"date":"17/9/2014","time":"23:16:54","errors":[]}
